serial2parallel.v
module serial2parallel (iReset, Clock, i1b, o11b);
  input Clock, i1b, iReset;
  output reg [10:0] o11b;

  reg recieving;
  reg [10:0] buffer_11b;
  reg [3:0] cont;

  always @ (negedge i1b) begin
    recieving <= 1;
  end

  always @(negedge Clock) begin
    if (!iReset) begin
      if (recieving == 1) begin
        buffer_11b[10-cont] <= i1b;
        cont <= cont + 1;
        if (cont == 11) begin
          o11b <= buffer_11b;
          buffer_11b <= 0;
          cont <= 0;
          recieving <= 0;
        end
      end
    end else begin
      recieving <= 0;
      buffer_11b <= 0;
      cont <= 0;
    end
  end
endmodule //serial2parallel

Pruebas/s2p_tb.v
`include "../serial2parallel.v"

module testbench;
  reg wClock, wReset, w1b;
  wire [9:0] w10b;

  serial2parallel s2p(.Clock(wClock), .iReset(wReset), .i1b(w1b), .o11b(w10b));

  always begin
    #5 wClock = ~wClock;
  end

  initial begin
    wClock <= 1;
    wReset <= 0;
    w1b <= 1;

    #10 wReset <= 1;
    #20 wReset <= 0;

    #20 w1b <= 1;
    #10 w1b <= 0;//inicia
    #10 w1b <= 1;
    #10 w1b <= 1;
    #10 w1b <= 0;
    #10 w1b <= 1;
    #10 w1b <= 0;
    #10 w1b <= 0;
    #10 w1b <= 0;
    #10 w1b <= 1;
    #10 w1b <= 1;
    #10 w1b <= 1; //termina 011010001 11 --> 3

    #40 w1b <= 1;
    #10 w1b <= 0;//inicia
    #10 w1b <= 1;
    #10 w1b <= 1;
    #10 w1b <= 1;
    #10 w1b <= 1;
    #10 w1b <= 0;
    #10 w1b <= 0;
    #10 w1b <= 0;
    #10 w1b <= 0;
    #10 w1b <= 1;
    #10 w1b <= 1; //termina 011110000 11 --> 3

    #40 w1b <= 1;
    #10 w1b <= 0;//inicia
    #10 w1b <= 1;
    #10 w1b <= 0;
    #10 w1b <= 0;
    #10 w1b <= 0;
    #10 w1b <= 0;
    #10 w1b <= 1;
    #10 w1b <= 1;
    #10 w1b <= 0;
    #10 w1b <= 1;
    #10 w1b <= 1; //termina 010000110 11 --> 2
    #60
    $finish;
  end

  initial begin
    $dumpfile("waves.vcd");
    $dumpvars(0, testbench);
  end
endmodule //testbench

Pruebas/waves.vcd
$date
	Wed May 23 11:39:47 2018
$end
$version
	Icarus Verilog
$end
$timescale
	1s
$end
$scope module testbench $end
$var wire 10 ! w10b [9:0] $end
$var reg 1 " w1b $end
$var reg 1 # wClock $end
$var reg 1 $ wReset $end
$scope module s2p $end
$var wire 1 % Clock $end
$var wire 1 & i1b $end
$var wire 1 ' iReset $end
$var reg 11 ( buffer_11b [10:0] $end
$var reg 4 ) cont [3:0] $end
$var reg 11 * o11b [10:0] $end
$var reg 1 + recieving $end
$upscope $end
$upscope $end
$enddefinitions $end
#0
$dumpvars
x+
bx *
bx )
bx (
0'
1&
1%
0$
1#
1"
bx !
$end
#5
0#
0%
#10
1$
1'
1#
1%
#15
b0 )
b0 (
0+
0#
0%
#20
1#
1%
#25
0#
0%
#30
0$
0'
1#
1%
#35
0#
0%
#40
1#
1%
#45
0#
0%
#50
1#
1%
#55
0#
0%
#60
1+
0"
0&
1#
1%
#65
b1 )
b0 (
0#
0%
#70
1"
1&
1#
1%
#75
b10 )
b1000000000 (
0#
0%
#80
1#
1%
#85
b11 )
b1100000000 (
0#
0%
#90
0"
0&
1#
1%
#95
b100 )
b1100000000 (
0#
0%
#100
1"
1&
1#
1%
#105
b101 )
b1101000000 (
0#
0%
#110
0"
0&
1#
1%
#115
b110 )
b1101000000 (
0#
0%
#120
1#
1%
#125
b111 )
b1101000000 (
0#
0%
#130
1#
1%
#135
b1000 )
b1101000000 (
0#
0%
#140
1"
1&
1#
1%
#145
b1001 )
b1101000100 (
0#
0%
#150
1#
1%
#155
b1010 )
b1101000110 (
0#
0%
#160
1#
1%
#165
b1011 )
b1101000111 (
0#
0%
#170
1#
1%
#175
b1101000111 !
0+
b0 (
b1101000111 *
b0 )
0#
0%
#180
1#
1%
#185
0#
0%
#190
1#
1%
#195
0#
0%
#200
1#
1%
#205
0#
0%
#210
1+
0"
0&
1#
1%
#215
b1 )
b0 (
0#
0%
#220
1"
1&
1#
1%
#225
b10 )
b1000000000 (
0#
0%
#230
1#
1%
#235
b11 )
b1100000000 (
0#
0%
#240
1#
1%
#245
b100 )
b1110000000 (
0#
0%
#250
1#
1%
#255
b101 )
b1111000000 (
0#
0%
#260
0"
0&
1#
1%
#265
b110 )
b1111000000 (
0#
0%
#270
1#
1%
#275
b111 )
b1111000000 (
0#
0%
#280
1#
1%
#285
b1000 )
b1111000000 (
0#
0%
#290
1#
1%
#295
b1001 )
b1111000000 (
0#
0%
#300
1"
1&
1#
1%
#305
b1010 )
b1111000010 (
0#
0%
#310
1#
1%
#315
b1011 )
b1111000011 (
0#
0%
#320
1#
1%
#325
b1111000011 !
0+
b0 (
b1111000011 *
b0 )
0#
0%
#330
1#
1%
#335
0#
0%
#340
1#
1%
#345
0#
0%
#350
1#
1%
#355
0#
0%
#360
1+
0"
0&
1#
1%
#365
b1 )
b0 (
0#
0%
#370
1"
1&
1#
1%
#375
b10 )
b1000000000 (
0#
0%
#380
0"
0&
1#
1%
#385
b11 )
b1000000000 (
0#
0%
#390
1#
1%
#395
b100 )
b1000000000 (
0#
0%
#400
1#
1%
#405
b101 )
b1000000000 (
0#
0%
#410
1#
1%
#415
b110 )
b1000000000 (
0#
0%
#420
1"
1&
1#
1%
#425
b111 )
b1000010000 (
0#
0%
#430
1#
1%
#435
b1000 )
b1000011000 (
0#
0%
#440
0"
0&
1#
1%
#445
b1001 )
b1000011000 (
0#
0%
#450
1"
1&
1#
1%
#455
b1010 )
b1000011010 (
0#
0%
#460
1#
1%
#465
b1011 )
b1000011011 (
0#
0%
#470
1#
1%
#475
b1000011011 !
0+
b0 (
b1000011011 *
b0 )
0#
0%
